{
  "$schema": "https://developer.microsoft.com/json-schemas/fabric/item/report/definition/visualContainer/2.6.0/schema.json",
  "name": "0f6185b7ff1dbf9c1919",
  "position": {
    "x": 511.9266055045872,
    "y": 245.22935779816515,
    "z": 6000,
    "height": 85.87155963302753,
    "width": 231.19266055045873,
    "tabOrder": 6000
  },
  "visual": {
    "visualType": "kpi",
    "query": {
      "queryState": {
        "Goal": {
          "projections": [
            {
              "field": {
                "Measure": {
                  "Expression": {
                    "SourceRef": {
                      "Entity": "fact_daily_air_quality"
                    }
                  },
                  "Property": "AQI target"
                }
              },
              "queryRef": "fact_daily_air_quality.AQI target",
              "nativeQueryRef": "AQI target"
            }
          ]
        },
        "Indicator": {
          "projections": [
            {
              "field": {
                "Measure": {
                  "Expression": {
                    "SourceRef": {
                      "Entity": "fact_daily_air_quality"
                    }
                  },
                  "Property": "Drill AQI Change %"
                }
              },
              "queryRef": "fact_daily_air_quality.Drill AQI Change %",
              "nativeQueryRef": "Drill AQI Change %",
              "format": "0.0 %;-0.0 %;0.0 %"
            }
          ]
        },
        "TrendLine": {
          "projections": [
            {
              "field": {
                "Column": {
                  "Expression": {
                    "SourceRef": {
                      "Entity": "dim_date"
                    }
                  },
                  "Property": "date"
                }
              },
              "queryRef": "dim_date.date",
              "nativeQueryRef": "date"
            }
          ]
        }
      },
      "sortDefinition": {
        "isDefaultSort": true
      }
    },
    "objects": {
      "lastDate": [
        {
          "properties": {
            "show": {
              "expr": {
                "Literal": {
                  "Value": "false"
                }
              }
            }
          }
        }
      ],
      "goals": [
        {
          "properties": {
            "showGoal": {
              "expr": {
                "Literal": {
                  "Value": "false"
                }
              }
            }
          }
        }
      ],
      "status": [
        {
          "properties": {
            "direction": {
              "expr": {
                "Literal": {
                  "Value": "'Negative'"
                }
              }
            }
          }
        }
      ]
    },
    "visualContainerObjects": {
      "title": [
        {
          "properties": {
            "text": {
              "expr": {
                "Literal": {
                  "Value": "'PM2.5'"
                }
              }
            },
            "alignment": {
              "expr": {
                "Literal": {
                  "Value": "'center'"
                }
              }
            }
          }
        }
      ],
      "border": [
        {
          "properties": {
            "show": {
              "expr": {
                "Literal": {
                  "Value": "true"
                }
              }
            },
            "color": {
              "solid": {
                "color": {
                  "expr": {
                    "ThemeDataColor": {
                      "ColorId": 0,
                      "Percent": -0.1
                    }
                  }
                }
              }
            },
            "radius": {
              "expr": {
                "Literal": {
                  "Value": "14D"
                }
              }
            }
          }
        }
      ],
      "dropShadow": [
        {
          "properties": {
            "show": {
              "expr": {
                "Literal": {
                  "Value": "true"
                }
              }
            },
            "preset": {
              "expr": {
                "Literal": {
                  "Value": "'BottomLeft'"
                }
              }
            },
            "angle": {
              "expr": {
                "Literal": {
                  "Value": "135L"
                }
              }
            },
            "shadowDistance": {
              "expr": {
                "Literal": {
                  "Value": "10L"
                }
              }
            },
            "shadowBlur": {
              "expr": {
                "Literal": {
                  "Value": "10L"
                }
              }
            },
            "shadowSpread": {
              "expr": {
                "Literal": {
                  "Value": "3L"
                }
              }
            },
            "transparency": {
              "expr": {
                "Literal": {
                  "Value": "70L"
                }
              }
            },
            "color": {
              "solid": {
                "color": {
                  "expr": {
                    "Literal": {
                      "Value": "'#F5C4AF'"
                    }
                  }
                }
              }
            }
          }
        }
      ]
    },
    "drillFilterOtherVisuals": true
  },
  "filterConfig": {
    "filters": [
      {
        "name": "0b139e41ae8faa3f260b",
        "field": {
          "Column": {
            "Expression": {
              "SourceRef": {
                "Entity": "dim_parameter"
              }
            },
            "Property": "parameter_name"
          }
        },
        "type": "Categorical",
        "filter": {
          "Version": 2,
          "From": [
            {
              "Name": "d",
              "Entity": "dim_parameter",
              "Type": 0
            }
          ],
          "Where": [
            {
              "Condition": {
                "In": {
                  "Expressions": [
                    {
                      "Column": {
                        "Expression": {
                          "SourceRef": {
                            "Source": "d"
                          }
                        },
                        "Property": "parameter_name"
                      }
                    }
                  ],
                  "Values": [
                    [
                      {
                        "Literal": {
                          "Value": "'PM2.5 - Local Conditions'"
                        }
                      }
                    ]
                  ]
                }
              }
            }
          ]
        },
        "howCreated": "User",
        "objects": {
          "general": [
            {
              "properties": {}
            }
          ]
        }
      }
    ]
  }
}